{
  "common_0278_rival_01": "Ta-ta-tachán![npcn:4]",
  "common_0278_rival_02": "[BD06:0]Aqui estamos, este é seu quarto,\n[trnm:0]![npcn:4]",
  "common_0278_rival_a": "Na verdade, é novo pra mim também.\nNunca estive aqui antes.[npcn:4]",
  "common_0278_rival_b": "Veja sua nova cama? Parece confortável.\nE deve estar bem cansado de tudo isso\\r\nmuita coisa no primeiro dia, hein?[npcn:4]",
  "common_0278_rival_c": "Rápido descanso em uma cama é tudo que\nprecisa  hoje!não é?[npcn:4]",
  "common_0278_rival_03": "I’ll see you tomorrow, when you’ve rested up.\nThen we can battle even more! Take care![npcn:4]",
  "common_0278_kari_01": "Seems like it’s time for a good rest!"
}