{
  "common_1120_rival_01": "Whoa, what happened? This place is a mess![npcn:4]",
  "common_1120_botan_01": "It looks like something went berserk in here.[npcn:8]",
  "common_1120_friend_01": "Yeah, but what...?[npcn:6]",
  "common_1120_hakase_01a": "Hello, children.[npcn:B]",
  "common_1120_hakase_01b": "Hello, children.[npcn:E]",
  "common_1120_botan_02": "Gah! Professor! Y-you scared us.[npcn:8]",
  "common_1120_hakase_02a": "I’m sorry.[npcn:B]",
  "common_1120_hakase_02b": "I’m sorry.[npcn:E]",
  "common_1120_rival_02": "Why is everything in here all busted up?[npcn:4]",
  "common_1120_hakase_03a": "I’m sorry. Hello, children.[npcn:B]",
  "common_1120_hakase_03b": "I’m sorry. Hello, children.[npcn:E]",
  "common_1120_friend_02": "...Come again?[npcn:6]",
  "common_1120_hakase_04a": "I’m s-s-s-s-s-sorry. Sorry. S-s-s-s-s-sorry.\nI-I-I I-I-I’m sssssssssorrrrrrrrrrrr-rrrrrry-eeeeee—\\r\nHello, children. Hello. Hello.[npcn:B]",
  "common_1120_hakase_04b": "I’m s-s-s-s-s-sorry. Sorry. S-s-s-s-s-sorry.\nI-I-I I-I-I’m sssssssssorrrrrrrrrrrr-rrrrrry-eeeeee—\\r\nHello, children. Hello. Hello.[npcn:E]",
  "common_1120_friend_03": "What the heck?![npcn:6]",
  "common_1120_botan_03": "Stop that! You’re creeping us out![npcn:8]",
  "common_1120_hakase_05a": "...Hello, child. Childrenen. Childnen. Childeren.\nChildren.[npcn:B]",
  "common_1120_hakase_05b": "...Hello, child. Childrenen. Childnen. Childeren.\nChildren.[npcn:E]",
  "common_1120_hakase_06a": "...Initiating restart.[npcn:B]",
  "common_1120_hakase_06b": "...Initiating restart.[npcn:E]",
  "common_1120_rival_03": "The professor must be having some...some weird\nconnection problems or something, huh?[npcn:4]",
  "common_1120_friend_04": "Well, it was definitely weird, at least.\nAlmost like... I dunno...[npcn:6]",
  "common_1120_botan_04": "If [s;:gs]he meant it as a joke, it wasn’t funny.\nI’ve still got goosebumps and all...[npcn:8]",
  "common_1120_all_01": "... ... ...",
  "common_1120_rival_04": "Looking at the damage, I have a feeling...maybe\nsome ferocious Pokémon battled here...[npcn:4]",
  "common_1120_friend_05": "That...that was almost like— No, it can’t be...[npcn:6]",
  "common_1120_botan_06": "Have you disabled the lock yet? I’m all for\nleaving this place as soon as we can.[npcn:8]",
  "common_1120_stopper_01": "Oops! Still got to disable that lock!",
  "common_1120_stopper_out": "Better disable the lock from inside the research\nstation..."
}